robinwould/__init__.py
robinwould/_utils.py
robinwould/crawler.py
robinwould/exceptions.py
robinwould/fields.py
robinwould/interfaces.py
robinwould/spider.py
robinwould-0.1.1.dist-info/LICENSE
robinwould-0.1.1.dist-info/WHEEL
robinwould-0.1.1.dist-info/METADATA
robinwould-0.1.1.dist-info/RECORD
