Metadata-Version: 2.1
Name: robinwould
Version: 0.1.1
Summary: RobinWould is framework for fast and easy development on web scraping tools based.
Author-email: Lucas Calegario <lucas.c.calegario@outlook.com>
Classifier: License :: OSI Approved :: MIT License
Requires-Dist: aiohttp >= 3.8.0, <3.9.0
Requires-Dist: scrapy >= 2.6.0, <2.7.0
Requires-Dist: pytest-cov >=3.0.0, <3.1.0 ; extra == "coverage"
Requires-Dist: pylint >=2.15.0, <2.16.0 ; extra == "lint"
Requires-Dist: pytest >=7.1.0, <7.2.0 ; extra == "test"
Requires-Dist: anyio >=3.6.0, <3.7.0 ; extra == "test"
Requires-Dist: trio >=0.21.0, < 0.22.0 ; extra == "test"
Project-URL: Home, https://github.com/xlurio/robinwould
Provides-Extra: coverage
Provides-Extra: lint
Provides-Extra: test
